certbot_dns_myloc/__init__.py
certbot_dns_myloc/dns_myloc.py
certbot_dns_myloc/version.py
certbot_dns_myloc-1.0.1.dist-info/LICENSE
certbot_dns_myloc-1.0.1.dist-info/METADATA
certbot_dns_myloc-1.0.1.dist-info/WHEEL
certbot_dns_myloc-1.0.1.dist-info/entry_points.txt
certbot_dns_myloc-1.0.1.dist-info/top_level.txt
certbot_dns_myloc-1.0.1.dist-info/RECORD
